metomi/rose/__init__.py
metomi/rose/app_run.py
metomi/rose/c3.py
metomi/rose/check_software.py
metomi/rose/checksum.py
metomi/rose/config.py
metomi/rose/config_cli.py
metomi/rose/config_diff.py
metomi/rose/config_dump.py
metomi/rose/config_processor.py
metomi/rose/config_tree.py
metomi/rose/date.py
metomi/rose/date_cli.py
metomi/rose/env.py
metomi/rose/env_cat.py
metomi/rose/external.py
metomi/rose/fs_util.py
metomi/rose/host_select.py
metomi/rose/host_select_client.py
metomi/rose/job_runner.py
metomi/rose/macro.py
metomi/rose/meta_type.py
metomi/rose/metadata_check.py
metomi/rose/metadata_gen.py
metomi/rose/metadata_graph.py
metomi/rose/namelist_dump.py
metomi/rose/opt_parse.py
metomi/rose/popen.py
metomi/rose/reporter.py
metomi/rose/resource.py
metomi/rose/rose.py
metomi/rose/run.py
metomi/rose/run_source_vc.py
metomi/rose/scheme_handler.py
metomi/rose/section.py
metomi/rose/suite_engine_proc.py
metomi/rose/task_env.py
metomi/rose/task_run.py
metomi/rose/unicode_utils.py
metomi/rose/upgrade.py
metomi/rose/variable.py
metomi/rose/apps/__init__.py
metomi/rose/apps/fcm_make.py
metomi/rose/apps/rose_ana.py
metomi/rose/apps/rose_ana_v1.py
metomi/rose/apps/rose_arch.py
metomi/rose/apps/rose_bunch.py
metomi/rose/apps/rose_prune.py
metomi/rose/apps/ana_builtin/__init__.py
metomi/rose/apps/ana_builtin/grepper.py
metomi/rose/apps/comparisons/cumf.py
metomi/rose/apps/comparisons/exact.py
metomi/rose/apps/comparisons/mandatory.py
metomi/rose/apps/comparisons/output_grepper.py
metomi/rose/apps/comparisons/prohibited.py
metomi/rose/apps/comparisons/within.py
metomi/rose/apps/rose_arch_compressions/__init__.py
metomi/rose/apps/rose_arch_compressions/rose_arch_gzip.py
metomi/rose/apps/rose_arch_compressions/rose_arch_tar.py
metomi/rose/config_processors/__init__.py
metomi/rose/config_processors/env.py
metomi/rose/config_processors/fileinstall.py
metomi/rose/etc/lib/bash/rose_log
metomi/rose/etc/lib/bash/rose_usage
metomi/rose/etc/rose-meta/fcm_make/HEAD/rose-meta.conf
metomi/rose/etc/rose-meta/rose-suite-info/rose-meta.conf
metomi_rose-2.6.3.dist-info/licenses/COPYING
metomi_rose-2.6.3.dist-info/METADATA
metomi_rose-2.6.3.dist-info/WHEEL
metomi_rose-2.6.3.dist-info/entry_points.txt
metomi_rose-2.6.3.dist-info/top_level.txt
metomi_rose-2.6.3.dist-info/RECORD
