Metadata-Version: 2.4
Name: metomi-rose
Version: 2.6.3
Summary: Rose, a framework for meteorological suites.
Author-email: "British Crown (Met Office) & Contributors" <metomi@metoffice.gov.uk>
License: GPL
Project-URL: Homepage, https://metomi.github.io/rose/doc/html/index.html
Project-URL: Repository, https://github.com/metomi/rose
Project-URL: Changelog, https://github.com/metomi/rose/blob/master/CHANGES.md
Keywords: hpc,weather-modelling,weather-model,meteorological-suites,meteorological-modelling,meteorological-models,workflows,workflow-automation
Classifier: Environment :: Console
Classifier: Environment :: Web Environment
Classifier: Intended Audience :: Developers
Classifier: Intended Audience :: System Administrators
Classifier: Intended Audience :: Science/Research
Classifier: Operating System :: POSIX :: Linux
Classifier: Programming Language :: Python :: 3
Classifier: Topic :: Scientific/Engineering :: Atmospheric Science
Requires-Python: >=3.12
License-File: COPYING
Requires-Dist: aiofiles
Requires-Dist: jinja2>=2.10.1
Requires-Dist: keyring>=23.0.0
Requires-Dist: ldap3
Requires-Dist: metomi-isodatetime==1!3.*
Requires-Dist: psutil>=5.6.0
Requires-Dist: requests
Requires-Dist: sqlalchemy==1.*
Provides-Extra: docs
Requires-Dist: cylc-sphinx-extensions[all]>=1.2.0; extra == "docs"
Requires-Dist: hieroglyph>=2.1.0; extra == "docs"
Requires-Dist: sphinx; extra == "docs"
Requires-Dist: sphinx-copybutton; extra == "docs"
Requires-Dist: sphinx_rtd_theme; extra == "docs"
Requires-Dist: sphinxcontrib-httpdomain; extra == "docs"
Requires-Dist: sphinxcontrib-svg2pdfconverter; extra == "docs"
Provides-Extra: graph
Requires-Dist: pygraphviz!=1.8,>1.0; extra == "graph"
Provides-Extra: tests
Requires-Dist: aiosmtpd; extra == "tests"
Requires-Dist: pytest; extra == "tests"
Requires-Dist: towncrier>=24.7.0; extra == "tests"
Provides-Extra: lint
Requires-Dist: flake8>=6.0.0; extra == "lint"
Requires-Dist: flake8-type-checking; extra == "lint"
Requires-Dist: mypy>=0.800; extra == "lint"
Requires-Dist: types-aiofiles; extra == "lint"
Provides-Extra: tutorials
Requires-Dist: cylc-flow[tutorials]>=8.6.1; extra == "tutorials"
Provides-Extra: rosa
Provides-Extra: all
Requires-Dist: metomi-rose[lint]; extra == "all"
Requires-Dist: metomi-rose[docs]; extra == "all"
Requires-Dist: metomi-rose[graph]; extra == "all"
Requires-Dist: metomi-rose[tests]; extra == "all"
Requires-Dist: metomi-rose[rosa]; extra == "all"
Requires-Dist: metomi-rose[tutorials]; extra == "all"
Dynamic: license-file
